{
  "bin": "python3",
  "executable": "./main.py",
  "n_gpus": 1,
  "jobs_per_gpu": 6,
  "_comments": ["calib_case1","calib_case2","calib_nevada","calib_borehole"],
  "hyperparameters": {
    "dataset_dir": ["~/Datasets/"],
    "outdir": ["./workspace"],
    "dataset": ["calib_case2"],
    "nlayers_run": [1],
    "nlayers_obs": [1],
    "nfeatures_run": [50,100],
    "nfeatures_obs": [100],
    "model": ["kw_jeu22"],
    "additive": [0,1],
    "nmc_train": [3],
    "nmc_test": [15],
    "lr": [5e-3,5e-7,5e-5],
    "lr_calib": [5e-3],
    "discrepancy_level": [5e-2],
    "iterations_fixed_noise": [10000],
    "iterations_free_noise": [5000],
    "test_interval": [1000],
    "batch_size_obs": [500],
    "batch_size_run": [500],
    "full_cov_W": [0],
    "rff_optim_run": [0],
    "rff_optim_obs": [0],
    "seed": [0],
    "init_batchsize": [100]
  }
}

